daty/__init__.py
daty/aboutdaty.py
daty/application.py
daty/config.py
daty/editor.py
daty/entity.py
daty/entitypopover.py
daty/entityselectable.py
daty/filterslist.py
daty/loadingpage.py
daty/open.py
daty/overlayedlistboxrow.py
daty/page.py
daty/property.py
daty/qualifierproperty.py
daty/roundedbutton.py
daty/sidebarentity.py
daty/sidebarlist.py
daty/statements.py
daty/triplet.py
daty/usersetup.py
daty/util.py
daty/value.py
daty/values.py
daty/wikidata.py
daty/po/build_template
daty/po/daty.pot
daty/po/it_IT.po
daty/po/setup.pot
daty/po/it_IT/LC_MESSAGES/daty.mo
daty/resources/compile-resources.sh
daty/resources/daty.gresource
daty/resources/daty.gresource.xml
daty/resources/ml.prevete.Daty.desktop
daty/resources/ml.prevete.DatyNightly.desktop
daty/resources/update-shebang.py
daty/resources/user-config.py
daty/resources/user-password.py
daty/resources/gtk/#editor.ui#
daty/resources/gtk/aboutdaty.ui
daty/resources/gtk/aboutdaty.ui~
daty/resources/gtk/closebutton.ui
daty/resources/gtk/closebutton.ui~
daty/resources/gtk/constraintlist.ui~
daty/resources/gtk/editablewidget.ui
daty/resources/gtk/editor.ui
daty/resources/gtk/editor.ui~
daty/resources/gtk/entity.css
daty/resources/gtk/entity.ui
daty/resources/gtk/entity.ui~
daty/resources/gtk/entitypopover.ui
daty/resources/gtk/entitypopover.ui~
daty/resources/gtk/entitysearch.ui
daty/resources/gtk/entityselectable.ui
daty/resources/gtk/entityselectable.ui~
daty/resources/gtk/filterslist.ui
daty/resources/gtk/filterslist.ui~
daty/resources/gtk/loadingpage.ui
daty/resources/gtk/loadingpage.ui~
daty/resources/gtk/open.ui
daty/resources/gtk/open.ui~
daty/resources/gtk/page.ui
daty/resources/gtk/page.ui~
daty/resources/gtk/property.css
daty/resources/gtk/property.ui
daty/resources/gtk/qualifier.ui
daty/resources/gtk/qualifierproperty.ui
daty/resources/gtk/qualifierproperty.ui~
daty/resources/gtk/qualifiersnak.css
daty/resources/gtk/roundedbutton.css
daty/resources/gtk/roundedbutton.ui
daty/resources/gtk/roundedbutton.ui~
daty-1.0b0.dist-info/LICENSE
daty-1.0b0.dist-info/METADATA
daty-1.0b0.dist-info/WHEEL
daty-1.0b0.dist-info/entry_points.txt
daty-1.0b0.dist-info/top_level.txt
daty-1.0b0.dist-info/RECORD
