Metadata-Version: 2.1
Name: daty
Version: 1.0b0
Summary: Advanced Wikidata editor
Home-page: https://gitlab.com/tallero/daty
Author: Pellegrino Prevete
Author-email: pellegrinoprevete@gmail.com
License: UNKNOWN
Platform: UNKNOWN
Classifier: Programming Language :: Python :: 3
Classifier: License :: OSI Approved :: GNU Affero General Public License v3 or later (AGPLv3+)
Classifier: Operating System :: Unix
Requires-Dist: appdirs
Requires-Dist: bleach
Requires-Dist: beautifulsoup4
Requires-Dist: pygobject
Requires-Dist: pywikibot
Requires-Dist: requests
Requires-Dist: setproctitle
